HISTORY.rst
LICENSE
MANIFEST.in
README.rst
setup.cfg
setup.py
docs/Makefile
docs/conf.py
docs/contributing.rst
docs/history.rst
docs/index.rst
docs/installation.rst
docs/make.bat
docs/readme.rst
docs/usage.rst
gazta/__init__.py
gazta.egg-info/PKG-INFO
gazta.egg-info/SOURCES.txt
gazta.egg-info/dependency_links.txt
gazta.egg-info/not-zip-safe
gazta.egg-info/requires.txt
gazta.egg-info/top_level.txt
tests/__init__.py
tests/test_gazta.py