Metadata-Version: 1.1
Name: gazta
Version: 0.2.1
Summary: Winning a handmade Cheese
Home-page: https://www.codesyntax.com
Author: CodeSyntax
Author-email: info@codesyntax.com
License: GNU General Public License v3
Keywords: gazta
Platform: UNKNOWN
Classifier: Intended Audience :: Developers
Classifier: Programming Language :: Python :: 2
Classifier: Programming Language :: Python :: 2.6
Classifier: Programming Language :: Python :: 2.7
Classifier: Programming Language :: Python :: 3
Classifier: Programming Language :: Python :: 3.3
Classifier: Programming Language :: Python :: 3.4
Classifier: Programming Language :: Python :: 3.5
